fivcglue/__about__.py
fivcglue/__init__.py
fivcglue/lazy.py
fivcglue/fixtures/configs_basics.yml
fivcglue/fixtures/configs_loggers.yml
fivcglue/implements/__init__.py
fivcglue/implements/caches_mem.py
fivcglue/implements/caches_redis.py
fivcglue/implements/configs_jsonfile.py
fivcglue/implements/configs_yamlfile.py
fivcglue/implements/loggers_builtin.py
fivcglue/implements/mutexes_redis.py
fivcglue/implements/queues_redis.py
fivcglue/implements/utils.py
fivcglue/interfaces/__init__.py
fivcglue/interfaces/caches.py
fivcglue/interfaces/configs.py
fivcglue/interfaces/loggers.py
fivcglue/interfaces/mutexes.py
fivcglue/interfaces/queues.py
fivcglue/interfaces/utils.py
fivcglue-0.1.5.dist-info/licenses/LICENSE
fivcglue-0.1.5.dist-info/METADATA
fivcglue-0.1.5.dist-info/WHEEL
fivcglue-0.1.5.dist-info/top_level.txt
fivcglue-0.1.5.dist-info/RECORD
