Metadata-Version: 2.4
Name: fivcglue
Version: 0.1.5
Summary: A Domain-Driven Design (DDD) programming package for Python, similar to zope.interface
Author-email: Charlie ZHANG <sunnypig2002@gmail.com>
License-Expression: MIT
Project-URL: Documentation, https://github.com/5C-Plus/fivcglue#readme
Project-URL: Issues, https://github.com/5C-Plus/fivcglue/issues
Project-URL: Source, https://github.com/5C-Plus/fivcglue
Keywords: ddd,domain-driven-design,interface,architecture
Classifier: Development Status :: 4 - Beta
Classifier: Programming Language :: Python
Classifier: Programming Language :: Python :: 3.10
Classifier: Programming Language :: Python :: 3.11
Classifier: Programming Language :: Python :: 3.12
Classifier: Programming Language :: Python :: 3.13
Classifier: Programming Language :: Python :: Implementation :: CPython
Classifier: Intended Audience :: Developers
Classifier: Topic :: Software Development :: Libraries :: Python Modules
Classifier: Topic :: Software Development :: Object Brokering
Requires-Python: >=3.10
License-File: LICENSE
Provides-Extra: yaml
Requires-Dist: PyYAML>=6.0.1; extra == "yaml"
Provides-Extra: dev
Requires-Dist: pytest>=8.2.0; extra == "dev"
Requires-Dist: pytest-asyncio>=0.21.0; extra == "dev"
Requires-Dist: pytest-cov>=4.1.0; extra == "dev"
Requires-Dist: ruff>=0.4.0; extra == "dev"
Requires-Dist: fakeredis>=2.13.0; extra == "dev"
Dynamic: license-file
